sentry_plugin_dingding/__init__.py
sentry_plugin_dingding/forms.py
sentry_plugin_dingding/plugin.py
sentry_plugin_dingding/valueDict.py
sentry_plugin_dingding-0.1.4.dist-info/LICENSE
sentry_plugin_dingding-0.1.4.dist-info/METADATA
sentry_plugin_dingding-0.1.4.dist-info/WHEEL
sentry_plugin_dingding-0.1.4.dist-info/entry_points.txt
sentry_plugin_dingding-0.1.4.dist-info/top_level.txt
sentry_plugin_dingding-0.1.4.dist-info/RECORD
