Metadata-Version: 2.1
Name: sentry-plugin-dingding
Version: 0.1.4
Summary: A Sentry extension which send errors stats to DingDing
Home-page: http://gogs.visionacademy.cn/tools/sentry-plugin-dingding
Author: wjj
Author-email: 88795596wjj@gmail.com
License: MIT
Keywords: sentry plugin dingding
Platform: UNKNOWN
Classifier: Programming Language :: Python :: 2.7
Classifier: License :: OSI Approved :: MIT License
Requires-Dist: sentry (>=9.0.0)
Requires-Dist: requests
